{
    "MEGCoordinateSystem": "ElektaNeuromag",
    "MEGCoordinateUnits": "m",
    "MEGCoordinateSystemDescription": "RAS orientation and the origin between the ears",
    "HeadCoilCoordinates": {
        "NAS": [
            0.0,
            0.08912168443202972,
            0.0
        ],
        "LPA": [
            -0.0690176784992218,
            -1.4901161193847656e-08,
            -3.725290298461914e-09
        ],
        "RPA": [
            0.07259812951087952,
            -1.4901161193847656e-08,
            1.862645149230957e-09
        ],
        "coil1": [
            -0.06594128906726837,
            -0.029940232634544373,
            0.010019409470260143
        ],
        "coil2": [
            -0.03853873163461685,
            0.09973149001598358,
            0.04937148466706276
        ],
        "coil3": [
            0.03525109961628914,
            0.09991855919361115,
            0.051654964685440063
        ],
        "coil4": [
            0.07427588850259781,
            -0.028725042939186096,
            0.00611048424616456
        ]
    },
    "HeadCoilCoordinateSystem": "ElektaNeuromag",
    "HeadCoilCoordinateUnits": "m",
    "AnatomicalLandmarkCoordinates": {
        "NAS": [
            0.0,
            0.08912168443202972,
            0.0
        ],
        "LPA": [
            -0.0690176784992218,
            -1.4901161193847656e-08,
            -3.725290298461914e-09
        ],
        "RPA": [
            0.07259812951087952,
            -1.4901161193847656e-08,
            1.862645149230957e-09
        ]
    },
    "AnatomicalLandmarkCoordinateSystem": "ElektaNeuromag",
    "AnatomicalLandmarkCoordinateUnits": "m"
}